rspro82/__init__.py
rspro82/__main__.py
rspro82/channels.py
rspro82/message.py
rspro82-23.8.0.post0.dist-info/LICENSE
rspro82-23.8.0.post0.dist-info/METADATA
rspro82-23.8.0.post0.dist-info/WHEEL
rspro82-23.8.0.post0.dist-info/entry_points.txt
rspro82-23.8.0.post0.dist-info/top_level.txt
rspro82-23.8.0.post0.dist-info/RECORD
