Metadata-Version: 2.1
Name: rspro82
Version: 23.8.0.post0
Summary: Utility for certain RadioShack PRO-branded radio scanners
Author-email: "Tim D. Smith" <tim@tds.xyz>
Project-URL: repository, https://github.com/tdsmith/rspro82
Classifier: License :: OSI Approved :: Apache Software License
Requires-Python: >=3.9
License-File: LICENSE
Requires-Dist: attrs
Requires-Dist: pandas
Requires-Dist: pyserial
Requires-Dist: typer
Requires-Dist: typing-extensions
Provides-Extra: dev
Requires-Dist: black ; extra == 'dev'
Requires-Dist: pip-tools ; extra == 'dev'
Requires-Dist: pyright ; extra == 'dev'
Requires-Dist: pytest ; extra == 'dev'
